{
  "count": 2,
  "sample": [
    {
      "listing_id": "172667459",
      "source": "rightmove",
      "source_url": "https://www.rightmove.co.uk/properties/172667459#/?channel=RES_LET",
      "title": "Albion Place, London, W6",
      "address": "Albion Place, London, W6",
      "postcode": null,
      "area_name": null,
      "city": null,
      "lat": null,
      "lng": null,
      "rent_pcm": 2000.0,
      "deposit": null,
      "bills_included": null,
      "council_tax_included": null,
      "other_fees": null,
      "property_type": "Apartment",
      "bedrooms": 1.0,
      "bathrooms": null,
      "furnished": null,
      "available_from": null,
      "min_tenancy_months": null,
      "max_tenancy_months": null,
      "distance_miles": null,
      "commute_minutes": null,
      "target_postcode_distance_miles": null,
      "summary": "This beautifully refurbished 1-bedroom flat in Albion Court is available in May, offering modern living in a secure gated development",
      "scraped_at": "2026-03-21T13:43:08.099846+00:00",
      "normalized_at": "2026-03-21T13:43:08.100852+00:00",
      "raw_data": {
        "source": "rightmove",
        "listing_id": "172667459",
        "title": "Albion Place, London, W6",
        "price": "£2,000 pcm",
        "bedrooms": "1",
        "address": "Albion Place, London, W6",
        "url": "https://www.rightmove.co.uk/properties/172667459#/?channel=RES_LET",
        "source_url": "https://www.rightmove.co.uk/properties/172667459#/?channel=RES_LET",
        "property_type": "Apartment",
        "summary": "This beautifully refurbished 1-bedroom flat in Albion Court is available in May, offering modern living in a secure gated development",
        "scraped_at": "2026-03-21T13:43:08.099846+00:00"
      }
    },
    {
      "listing_id": "87718020",
      "source": "rightmove",
      "source_url": "https://www.rightmove.co.uk/properties/87718020#/?channel=RES_LET",
      "title": "Rostrevor Road, Fulham",
      "address": "Rostrevor Road, Fulham",
      "postcode": null,
      "area_name": null,
      "city": null,
      "lat": null,
      "lng": null,
      "rent_pcm": 2250.0,
      "deposit": null,
      "bills_included": null,
      "council_tax_included": null,
      "other_fees": null,
      "property_type": "Flat",
      "bedrooms": 1.0,
      "bathrooms": null,
      "furnished": null,
      "available_from": null,
      "min_tenancy_months": null,
      "max_tenancy_months": null,
      "distance_miles": null,
      "commute_minutes": null,
      "target_postcode_distance_miles": null,
      "summary": "SHORT LET - An extraordinary one bedroom garden flat flat, available for 3/4 months only, forming the ground floor of this substantial converted house offering nice internal proportions with lovely high ceilings and an unusually large garden. Rostrevor Road is a sought after residential ...",
      "scraped_at": "2026-03-21T13:43:08.099846+00:00",
      "normalized_at": "2026-03-21T13:43:08.100852+00:00",
      "raw_data": {
        "source": "rightmove",
        "listing_id": "87718020",
        "title": "Rostrevor Road, Fulham",
        "price": "£2,250 pcm",
        "bedrooms": "1",
        "address": "Rostrevor Road, Fulham",
        "url": "https://www.rightmove.co.uk/properties/87718020#/?channel=RES_LET",
        "source_url": "https://www.rightmove.co.uk/properties/87718020#/?channel=RES_LET",
        "property_type": "Flat",
        "summary": "SHORT LET - An extraordinary one bedroom garden flat flat, available for 3/4 months only, forming the ground floor of this substantial converted house offering nice internal proportions with lovely high ceilings and an unusually large garden. Rostrevor Road is a sought after residential ...",
        "scraped_at": "2026-03-21T13:43:08.099846+00:00"
      }
    }
  ]
}